[
  { "w": 1, "v": "{$traits2=$majPro}{$traits2+$isAre}{$traits2+ very quick to trust other people. }" },
  { "w": 1, "v": "{$traits2=$majPro}{$traits2+$isAre}{$traits2+ very slow to trust other people. }" },
  { "w": 1, "v": "{$traits2=$majPro}{$traits2+$isAre}{$traits2+ very obstinate. }" },
  { "w": 1, "v": "{$traits2=$majPro}{$traits2+$isAre}{$traits2+ not very obstinate. }" },
  { "w": 1, "v": "{$traits2=$majPro}{$traits2+$isAre}{$traits2+ very optimistic. }" },
  { "w": 1, "v": "{$traits2=$majPro}{$traits2+$isAre}{$traits2+ very pessimistic. }" },
  { "w": 1, "v": "{$traits2=$majPro}{$traits2+$isAre}{$traits2+ an example of modesty. }" },
  { "w": 1, "v": "{$traits2=$majPro}{$traits2+$isAre}{$traits2+ }{mod}{$traits2+$mod}{$traits2+conceited. }" },
  { "w": 1, "v": "{$traits2=$majPro}{$traits2+$isAre}{$traits2+ very self-confident. }{%cha+1}" },
  { "w": 1, "v": "{$traits2=$majPro}{$traits2+{$traits2+$haveHas}{$traits2+ no self-confidence. }{%cha-1}" },
  { "w": 1, "v": "{$traits2=$majPro}{$traits2+rarely speak}{$traits2+$nbS}{$traits2+. }" },
  { "w": 1, "v": "{$traits2=$majPro}{$traits2+$isAre}{$traits2+ very talkative. }" },
  { "w": 1, "v": "{$traits2=$majPro}{$traits2+only talk}{$traits2+$nbS}{$traits2+ in whispers. }" },
  { "w": 1, "v": "{$traits2=$majPro}{$traits2+only talk}{$traits2+$nbS}{$traits2+ loudly. }" },
  { "w": 1, "v": "{$traits2=$majPro}{$traits2+$isAre}{$traits2+ very generous. }{%good+2}" },
  { "w": 1, "v": "{$traits2=$majPro}{$traits2+$isAre}{$traits2+ very greedy. }{%evil+2}" },
  { "w": 1, "v": "{$traits2=$majPro}{$traits2+$isAre}{$traits2+ materialistic. }" },
  { "w": 1, "v": "{$traits2=$majPro}{$traits2+$isAre}{$traits2+ non-materialistic. }{%chaotic+1}" },
  { "w": 1, "v": "{$traits2=$majPro}{$traits2+$isAre}{$traits2+ very cowardly. }" },
  { "w": 1, "v": "{$traits2=$majPro}{$traits2+$isAre}{$traits2+ very courageous, to a fault. }" },
  { "w": 1, "v": "{$traits2=$majPro}{$traits2+do}{$traits2+$nbDont}{$traits2+ care about risks or odds. }" },
  { "w": 1, "v": "{$traits2=$majPro}{$traits2+judge}{$traits2+$nbS}{$traits2+ people by their actions, not their words. }" },
  { "w": 1, "v": "{$traits2=$majPro}{$traits2+take}{$traits2+$nbS}{$traits2+ everything at face-value. }" },
  { "w": 2, "v": "{$traits2=$majPro}{$traits2+constantly look}{$traits2+$nbS}{$traits2+ for the loophole. }{%lawful-2}{%chaotic+2}{%int+1}" },
  { "w": 1, "v": "{$traits2=$majPro}{$traits2+$isAre}{$traits2+ a perfectionist. }{%str+1}{%dex+1}{%con+1}{%int+1}{%wis+1}{%cha+1}" },
  { "w": 1, "v": "{$traits2=$majPro}{$traits2+$isAre}{$traits2+ }{mod}{$traits2+$mod}{$traits2+lazy. }" },
  { "w": 1, "v": "{$traits2=$majPro}{$traits2+can't stand laziness. }{%lawful+2}" },
  { "w": 1, "v": "{$traits2=$majPro}{$traits2+can't keep a secret. }{%wis-1}" },
  { "w": 1, "v": "{$traits2=$majPro}{$traits2+$isAre}{$traits2+ very good at keeping secrets. }{%wis-1}" }
]
